{
"meta":{"test_sets":[],"test_metrics":[],"learn_metrics":[{"best_value":"Min","name":"Logloss"}],"launch_mode":"Train","parameters":"","iteration_count":500,"learn_sets":["learn"],"name":"experiment"},
"iterations":[
{"learn":[0.6702154828],"iteration":0,"passed_time":0.2284547375,"remaining_time":113.998914},
{"learn":[0.6517068188],"iteration":1,"passed_time":0.3209843852,"remaining_time":79.92511192},
{"learn":[0.6369587802],"iteration":2,"passed_time":0.4198896772,"remaining_time":69.56172319},
{"learn":[0.6253764087],"iteration":3,"passed_time":0.5112331918,"remaining_time":63.39291578},
{"learn":[0.615709253],"iteration":4,"passed_time":0.5992929968,"remaining_time":59.33000668},
{"learn":[0.6083555642],"iteration":5,"passed_time":0.6835608974,"remaining_time":56.27984722},
{"learn":[0.6019342762],"iteration":6,"passed_time":0.7788673231,"remaining_time":54.8545129},
{"learn":[0.5966784309],"iteration":7,"passed_time":0.8671333021,"remaining_time":53.32869808},
{"learn":[0.5926453806],"iteration":8,"passed_time":0.9579487604,"remaining_time":52.26142682},
{"learn":[0.5896051184],"iteration":9,"passed_time":1.055815629,"remaining_time":51.73496581},
{"learn":[0.5867681511],"iteration":10,"passed_time":1.153682602,"remaining_time":51.28643566},
{"learn":[0.5845438182],"iteration":11,"passed_time":1.243397155,"remaining_time":50.56481762},
{"learn":[0.5828749479],"iteration":12,"passed_time":1.31999675,"remaining_time":49.44910903},
{"learn":[0.5813255689],"iteration":13,"passed_time":1.413094743,"remaining_time":49.05457466},
{"learn":[0.5799026091],"iteration":14,"passed_time":1.505062767,"remaining_time":48.66369614},
{"learn":[0.5786920745],"iteration":15,"passed_time":1.601385652,"remaining_time":48.44191597},
{"learn":[0.577719936],"iteration":16,"passed_time":1.698021754,"remaining_time":48.24379453},
{"learn":[0.5768559404],"iteration":17,"passed_time":1.77619715,"remaining_time":47.56261256},
{"learn":[0.5760438051],"iteration":18,"passed_time":1.864589249,"remaining_time":47.20354887},
{"learn":[0.5754458407],"iteration":19,"passed_time":1.953041132,"remaining_time":46.87298717},
{"learn":[0.5749400798],"iteration":20,"passed_time":2.048271792,"remaining_time":46.7201042},
{"learn":[0.5743966597],"iteration":21,"passed_time":2.137476999,"remaining_time":46.4415457},
{"learn":[0.5739892911],"iteration":22,"passed_time":2.228918082,"remaining_time":46.22582283},
{"learn":[0.5736766192],"iteration":23,"passed_time":2.315882425,"remaining_time":45.9316681},
{"learn":[0.5733394476],"iteration":24,"passed_time":2.407243103,"remaining_time":45.73761895},
{"learn":[0.5730038349],"iteration":25,"passed_time":2.496330203,"remaining_time":45.51001986},
{"learn":[0.5726823121],"iteration":26,"passed_time":2.586969396,"remaining_time":45.31987127},
{"learn":[0.5724570669],"iteration":27,"passed_time":2.675046694,"remaining_time":45.09364426},
{"learn":[0.5722304873],"iteration":28,"passed_time":2.764683326,"remaining_time":44.90227056},
{"learn":[0.5720188105],"iteration":29,"passed_time":2.859350635,"remaining_time":44.79649328},
{"learn":[0.5718267139],"iteration":30,"passed_time":2.948196935,"remaining_time":44.60336653},
{"learn":[0.5716493107],"iteration":31,"passed_time":3.043036233,"remaining_time":44.50440491},
{"learn":[0.5714536323],"iteration":32,"passed_time":3.138523468,"remaining_time":44.4148624},
{"learn":[0.5712695917],"iteration":33,"passed_time":3.227779638,"remaining_time":44.23956797},
{"learn":[0.5711210466],"iteration":34,"passed_time":3.317164916,"remaining_time":44.07090532},
{"learn":[0.5709694964],"iteration":35,"passed_time":3.40609028,"remaining_time":43.90071916},
{"learn":[0.5708578478],"iteration":36,"passed_time":3.500322409,"remaining_time":43.80133176},
{"learn":[0.5707045065],"iteration":37,"passed_time":3.594495291,"remaining_time":43.70149538},
{"learn":[0.5705120975],"iteration":38,"passed_time":3.696018233,"remaining_time":43.68883091},
{"learn":[0.5704249901],"iteration":39,"passed_time":3.78341654,"remaining_time":43.50929021},
{"learn":[0.5703076839],"iteration":40,"passed_time":3.878044321,"remaining_time":43.4151791},
{"learn":[0.5702051298],"iteration":41,"passed_time":3.957663653,"remaining_time":43.15737984},
{"learn":[0.5701096706],"iteration":42,"passed_time":4.052172411,"remaining_time":43.06611143},
{"learn":[0.5700334981],"iteration":43,"passed_time":4.141630668,"remaining_time":42.9223542},
{"learn":[0.5699252693],"iteration":44,"passed_time":4.237990697,"remaining_time":42.85079483},
{"learn":[0.5698538514],"iteration":45,"passed_time":4.33405947,"remaining_time":42.77528259},
{"learn":[0.5698058798],"iteration":46,"passed_time":4.426453217,"remaining_time":42.66347463},
{"learn":[0.5696744361],"iteration":47,"passed_time":4.510250089,"remaining_time":42.47152167},
{"learn":[0.5695761164],"iteration":48,"passed_time":4.596844583,"remaining_time":42.30973279},
{"learn":[0.5695235514],"iteration":49,"passed_time":4.684397726,"remaining_time":42.15957953},
{"learn":[0.5694214436],"iteration":50,"passed_time":4.779745078,"remaining_time":42.08050078},
{"learn":[0.5693352214],"iteration":51,"passed_time":4.862626045,"remaining_time":41.89339361},
{"learn":[0.5691837036],"iteration":52,"passed_time":4.955252954,"remaining_time":41.79241642},
{"learn":[0.5691008552],"iteration":53,"passed_time":5.039348096,"remaining_time":41.62128242},
{"learn":[0.5690358824],"iteration":54,"passed_time":5.125269984,"remaining_time":41.46809351},
{"learn":[0.5689562914],"iteration":55,"passed_time":5.215941985,"remaining_time":41.35496859},
{"learn":[0.5688657867],"iteration":56,"passed_time":5.310828289,"remaining_time":41.27538477},
{"learn":[0.568768026],"iteration":57,"passed_time":5.396112393,"remaining_time":41.12209789},
{"learn":[0.5686888833],"iteration":58,"passed_time":5.487624005,"remaining_time":41.01766417},
{"learn":[0.5686159829],"iteration":59,"passed_time":5.577054122,"remaining_time":40.89839689},
{"learn":[0.5685457569],"iteration":60,"passed_time":5.671073706,"remaining_time":40.813137},
{"learn":[0.5684809049],"iteration":61,"passed_time":5.76155434,"remaining_time":40.70259356},
{"learn":[0.5684137722],"iteration":62,"passed_time":5.85291253,"remaining_time":40.59877421},
{"learn":[0.5683465142],"iteration":63,"passed_time":5.946801121,"remaining_time":40.51258264},
{"learn":[0.5682892956],"iteration":64,"passed_time":6.046041201,"remaining_time":40.46196804},
{"learn":[0.5682161752],"iteration":65,"passed_time":6.144156447,"remaining_time":40.4024833},
{"learn":[0.5681584262],"iteration":66,"passed_time":6.236654574,"remaining_time":40.30554374},
{"learn":[0.5681173876],"iteration":67,"passed_time":6.331488919,"remaining_time":40.22357666},
{"learn":[0.5680620769],"iteration":68,"passed_time":6.418044039,"remaining_time":40.08952146},
{"learn":[0.5679934137],"iteration":69,"passed_time":6.510495846,"remaining_time":39.99304591},
{"learn":[0.567908891],"iteration":70,"passed_time":6.594365966,"remaining_time":39.84483098},
{"learn":[0.567884134],"iteration":71,"passed_time":6.684178794,"remaining_time":39.7337295},
{"learn":[0.5678202276],"iteration":72,"passed_time":6.775097515,"remaining_time":39.62967998},
{"learn":[0.5677460022],"iteration":73,"passed_time":6.867787438,"remaining_time":39.53618174},
{"learn":[0.5676686824],"iteration":74,"passed_time":6.957311863,"remaining_time":39.42476722},
{"learn":[0.5676186229],"iteration":75,"passed_time":7.053773475,"remaining_time":39.35263097},
{"learn":[0.5675515685],"iteration":76,"passed_time":7.14847688,"remaining_time":39.27020416},
{"learn":[0.5674791066],"iteration":77,"passed_time":7.234430609,"remaining_time":39.14012458},
{"learn":[0.5674405929],"iteration":78,"passed_time":7.323670969,"remaining_time":39.02867693},
{"learn":[0.5673862415],"iteration":79,"passed_time":7.419153305,"remaining_time":38.95055485},
{"learn":[0.5672972294],"iteration":80,"passed_time":7.507085487,"remaining_time":38.83294838},
{"learn":[0.5672169483],"iteration":81,"passed_time":7.601904067,"remaining_time":38.75116951},
{"learn":[0.5671848466],"iteration":82,"passed_time":7.699381829,"remaining_time":38.68243642},
{"learn":[0.5671427599],"iteration":83,"passed_time":7.793224051,"remaining_time":38.59501435},
{"learn":[0.5670769351],"iteration":84,"passed_time":7.885064577,"remaining_time":38.49766823},
{"learn":[0.5669874461],"iteration":85,"passed_time":7.980923398,"remaining_time":38.41979403},
{"learn":[0.5668931381],"iteration":86,"passed_time":8.067709816,"remaining_time":38.29843855},
{"learn":[0.5668286252],"iteration":87,"passed_time":8.157756109,"remaining_time":38.19313087},
{"learn":[0.5667622078],"iteration":88,"passed_time":8.253714688,"remaining_time":38.11546895},
{"learn":[0.5666882955],"iteration":89,"passed_time":8.339255793,"remaining_time":37.98994305},
{"learn":[0.5666447543],"iteration":90,"passed_time":8.425838297,"remaining_time":37.86997652},
{"learn":[0.5665784445],"iteration":91,"passed_time":8.508350771,"remaining_time":37.73268603},
{"learn":[0.5665338197],"iteration":92,"passed_time":8.59549902,"remaining_time":37.6168613},
{"learn":[0.5664981546],"iteration":93,"passed_time":8.690409922,"remaining_time":37.53517477},
{"learn":[0.5664191543],"iteration":94,"passed_time":8.78568063,"remaining_time":37.45474374},
{"learn":[0.5663682378],"iteration":95,"passed_time":8.881164283,"remaining_time":37.37489969},
{"learn":[0.5663139501],"iteration":96,"passed_time":8.968461716,"remaining_time":37.26072239},
{"learn":[0.5662634262],"iteration":97,"passed_time":9.062214618,"remaining_time":37.17357425},
{"learn":[0.5661923558],"iteration":98,"passed_time":9.156129473,"remaining_time":37.08694867},
{"learn":[0.5661522887],"iteration":99,"passed_time":9.248716143,"remaining_time":36.99486457},
{"learn":[0.5661073439],"iteration":100,"passed_time":9.340814672,"remaining_time":36.90084212},
{"learn":[0.5660334692],"iteration":101,"passed_time":9.435293897,"remaining_time":36.81614677},
{"learn":[0.5660013403],"iteration":102,"passed_time":9.527488607,"remaining_time":36.72245609},
{"learn":[0.5659399084],"iteration":103,"passed_time":9.623481771,"remaining_time":36.64325751},
{"learn":[0.5658780122],"iteration":104,"passed_time":9.719265847,"remaining_time":36.56295247},
{"learn":[0.5658328436],"iteration":105,"passed_time":9.811741032,"remaining_time":36.47005629},
{"learn":[0.565790541],"iteration":106,"passed_time":9.905566341,"remaining_time":36.38212684},
{"learn":[0.5657457951],"iteration":107,"passed_time":10.00324868,"remaining_time":36.3080878},
{"learn":[0.5656898698],"iteration":108,"passed_time":10.09820574,"remaining_time":36.22383895},
{"learn":[0.5656396156],"iteration":109,"passed_time":10.18575664,"remaining_time":36.11313717},
{"learn":[0.5656136215],"iteration":110,"passed_time":10.27009753,"remaining_time":35.99160305},
{"learn":[0.565584018],"iteration":111,"passed_time":10.366127,"remaining_time":35.91122566},
{"learn":[0.5655481518],"iteration":112,"passed_time":10.45650416,"remaining_time":35.81121336},
{"learn":[0.5654994307],"iteration":113,"passed_time":10.54542201,"remaining_time":35.70642893},
{"learn":[0.5654994292],"iteration":114,"passed_time":10.57124517,"remaining_time":35.39069035},
{"learn":[0.5654339931],"iteration":115,"passed_time":10.66673509,"remaining_time":35.31057134},
{"learn":[0.5653817301],"iteration":116,"passed_time":10.75764469,"remaining_time":35.21519588},
{"learn":[0.5653197904],"iteration":117,"passed_time":10.8536778,"remaining_time":35.13648238},
{"learn":[0.5652686755],"iteration":118,"passed_time":10.94299088,"remaining_time":35.0359624},
{"learn":[0.5651915909],"iteration":119,"passed_time":11.0323681,"remaining_time":34.93583231},
{"learn":[0.5651481381],"iteration":120,"passed_time":11.1311203,"remaining_time":34.86524458},
{"learn":[0.5651024283],"iteration":121,"passed_time":11.22297621,"remaining_time":34.77282792},
{"learn":[0.5650219746],"iteration":122,"passed_time":11.31117715,"remaining_time":34.66921778},
{"learn":[0.5649548153],"iteration":123,"passed_time":11.40259247,"remaining_time":34.57560296},
{"learn":[0.5648851958],"iteration":124,"passed_time":11.49182913,"remaining_time":34.4754874},
{"learn":[0.5648344911],"iteration":125,"passed_time":11.58105984,"remaining_time":34.37552683},
{"learn":[0.5647733043],"iteration":126,"passed_time":11.67342819,"remaining_time":34.28495051},
{"learn":[0.5647339483],"iteration":127,"passed_time":11.76658601,"remaining_time":34.19664058},
{"learn":[0.5646721045],"iteration":128,"passed_time":11.85900013,"remaining_time":34.10611664},
{"learn":[0.5646013442],"iteration":129,"passed_time":11.94969469,"remaining_time":34.0106695},
{"learn":[0.5645609116],"iteration":130,"passed_time":12.04769194,"remaining_time":33.93586508},
{"learn":[0.5644896037],"iteration":131,"passed_time":12.14642241,"remaining_time":33.86275339},
{"learn":[0.5644261102],"iteration":132,"passed_time":12.23860937,"remaining_time":33.7712003},
{"learn":[0.5643688099],"iteration":133,"passed_time":12.33081891,"remaining_time":33.67969941},
{"learn":[0.5642938754],"iteration":134,"passed_time":12.42297096,"remaining_time":33.58803259},
{"learn":[0.5642326873],"iteration":135,"passed_time":12.51525104,"remaining_time":33.4967013},
{"learn":[0.5641608524],"iteration":136,"passed_time":12.60679379,"remaining_time":33.40340254},
{"learn":[0.5640848228],"iteration":137,"passed_time":12.70042076,"remaining_time":33.31559648},
{"learn":[0.5640076344],"iteration":138,"passed_time":12.79405528,"remaining_time":33.22772631},
{"learn":[0.5639418264],"iteration":139,"passed_time":12.89135042,"remaining_time":33.14918679},
{"learn":[0.5638811678],"iteration":140,"passed_time":12.98660376,"remaining_time":33.06518263},
{"learn":[0.5638340343],"iteration":141,"passed_time":13.07498867,"remaining_time":32.96370384},
{"learn":[0.5637881463],"iteration":142,"passed_time":13.16906989,"remaining_time":32.87662904},
{"learn":[0.563726094],"iteration":143,"passed_time":13.26807804,"remaining_time":32.80163737},
{"learn":[0.5636570818],"iteration":144,"passed_time":13.35872899,"remaining_time":32.70585373},
{"learn":[0.5635874501],"iteration":145,"passed_time":13.45447401,"remaining_time":32.62249178},
{"learn":[0.5635367215],"iteration":146,"passed_time":13.54486589,"remaining_time":32.52610653},
{"learn":[0.5634747691],"iteration":147,"passed_time":13.64254246,"remaining_time":32.44712801},
{"learn":[0.5634199243],"iteration":148,"passed_time":13.73744207,"remaining_time":32.36135683},
{"learn":[0.5633520946],"iteration":149,"passed_time":13.83517246,"remaining_time":32.28206907},
{"learn":[0.5633057634],"iteration":150,"passed_time":13.93288632,"remaining_time":32.20249884},
{"learn":[0.5632663431],"iteration":151,"passed_time":14.0234321,"remaining_time":32.10627875},
{"learn":[0.5632029377],"iteration":152,"passed_time":14.11670967,"remaining_time":32.01632846},
{"learn":[0.5631490018],"iteration":153,"passed_time":14.21297246,"remaining_time":31.93304202},
{"learn":[0.563095208],"iteration":154,"passed_time":14.31440531,"remaining_time":31.86109569},
{"learn":[0.5630569716],"iteration":155,"passed_time":14.40708225,"remaining_time":31.76946343},
{"learn":[0.5630089964],"iteration":156,"passed_time":14.50253774,"remaining_time":31.68388818},
{"learn":[0.5629429672],"iteration":157,"passed_time":14.5995367,"remaining_time":31.60152882},
{"learn":[0.5628723355],"iteration":158,"passed_time":14.69473576,"remaining_time":31.51512511},
{"learn":[0.5628068886],"iteration":159,"passed_time":14.78948389,"remaining_time":31.42765327},
{"learn":[0.5627325722],"iteration":160,"passed_time":14.88427493,"remaining_time":31.34018137},
{"learn":[0.5626517015],"iteration":161,"passed_time":14.97793832,"remaining_time":31.25026638},
{"learn":[0.5625949771],"iteration":162,"passed_time":15.07385664,"remaining_time":31.1649674},
{"learn":[0.562540676],"iteration":163,"passed_time":15.16807175,"remaining_time":31.07604944},
{"learn":[0.5624702265],"iteration":164,"passed_time":15.26304926,"remaining_time":30.98861516},
{"learn":[0.5623985679],"iteration":165,"passed_time":15.35787295,"remaining_time":30.90078052},
{"learn":[0.5623478403],"iteration":166,"passed_time":15.4480594,"remaining_time":30.80361546},
{"learn":[0.5622688474],"iteration":167,"passed_time":15.54450688,"remaining_time":30.71890645},
{"learn":[0.5622070379],"iteration":168,"passed_time":15.63699692,"remaining_time":30.62630757},
{"learn":[0.5621604584],"iteration":169,"passed_time":15.73197478,"remaining_time":30.53853927},
{"learn":[0.5620868404],"iteration":170,"passed_time":15.82182508,"remaining_time":30.44082135},
{"learn":[0.5620354208],"iteration":171,"passed_time":15.91486814,"remaining_time":30.34928343},
{"learn":[0.5619707902],"iteration":172,"passed_time":16.01701458,"remaining_time":30.27493507},
{"learn":[0.5619194558],"iteration":173,"passed_time":16.11342036,"remaining_time":30.1895117},
{"learn":[0.5618592407],"iteration":174,"passed_time":16.2059149,"remaining_time":30.0966991},
{"learn":[0.5618399871],"iteration":175,"passed_time":16.2982578,"remaining_time":30.00361095},
{"learn":[0.5617921678],"iteration":176,"passed_time":16.39105244,"remaining_time":29.91135558},
{"learn":[0.5617246635],"iteration":177,"passed_time":16.48431165,"remaining_time":29.81993456},
{"learn":[0.5616557608],"iteration":178,"passed_time":16.57793011,"remaining_time":29.72913725},
{"learn":[0.5615894733],"iteration":179,"passed_time":16.67414486,"remaining_time":29.6429242},
{"learn":[0.5615397486],"iteration":180,"passed_time":16.76674034,"remaining_time":29.55022193},
{"learn":[0.5614745603],"iteration":181,"passed_time":16.86099487,"remaining_time":29.46041962},
{"learn":[0.5614281154],"iteration":182,"passed_time":16.96088674,"remaining_time":29.38033387},
{"learn":[0.5613790204],"iteration":183,"passed_time":17.05743287,"remaining_time":29.29428689},
{"learn":[0.5613170035],"iteration":184,"passed_time":17.15458931,"remaining_time":29.20916559},
{"learn":[0.5612776451],"iteration":185,"passed_time":17.24666195,"remaining_time":29.11533254},
{"learn":[0.5612187768],"iteration":186,"passed_time":17.33830919,"remaining_time":29.0208063},
{"learn":[0.5611554944],"iteration":187,"passed_time":17.43405854,"remaining_time":28.93311843},
{"learn":[0.5610850442],"iteration":188,"passed_time":17.52895963,"remaining_time":28.84394944},
{"learn":[0.5610295586],"iteration":189,"passed_time":17.62732402,"remaining_time":28.76037077},
{"learn":[0.5610025158],"iteration":190,"passed_time":17.71908354,"remaining_time":28.66595191},
{"learn":[0.5609606153],"iteration":191,"passed_time":17.81755407,"remaining_time":28.58232631},
{"learn":[0.5608789289],"iteration":192,"passed_time":17.91363999,"remaining_time":28.49475377},
{"learn":[0.5608156618],"iteration":193,"passed_time":18.01283355,"remaining_time":28.41199518},
{"learn":[0.5607484774],"iteration":194,"passed_time":18.10301635,"remaining_time":28.31497429},
{"learn":[0.56069373],"iteration":195,"passed_time":18.20201903,"remaining_time":28.23170298},
{"learn":[0.5606729368],"iteration":196,"passed_time":18.29785097,"remaining_time":28.14339515},
{"learn":[0.5606071263],"iteration":197,"passed_time":18.39315454,"remaining_time":28.05420541},
{"learn":[0.5605840388],"iteration":198,"passed_time":18.4846895,"remaining_time":27.95925397},
{"learn":[0.5605138207],"iteration":199,"passed_time":18.58073529,"remaining_time":27.87110294},
{"learn":[0.5604563753],"iteration":200,"passed_time":18.67801561,"remaining_time":27.78470979},
{"learn":[0.560403944],"iteration":201,"passed_time":18.77322048,"remaining_time":27.69514704},
{"learn":[0.5603555112],"iteration":202,"passed_time":18.86815669,"remaining_time":27.60513564},
{"learn":[0.560323702],"iteration":203,"passed_time":18.95295169,"remaining_time":27.50036127},
{"learn":[0.5602666305],"iteration":204,"passed_time":19.04695069,"remaining_time":27.4090266},
{"learn":[0.5602090044],"iteration":205,"passed_time":19.14572509,"remaining_time":27.32448143},
{"learn":[0.5601900374],"iteration":206,"passed_time":19.24268564,"remaining_time":27.23723137},
{"learn":[0.5601309836],"iteration":207,"passed_time":19.33796002,"remaining_time":27.1475208},
{"learn":[0.5600828135],"iteration":208,"passed_time":19.43139326,"remaining_time":27.05519349},
{"learn":[0.5600110879],"iteration":209,"passed_time":19.53332655,"remaining_time":26.97459381},
{"learn":[0.5599791438],"iteration":210,"passed_time":19.63428788,"remaining_time":26.89246065},
{"learn":[0.5598910913],"iteration":211,"passed_time":19.72519918,"remaining_time":26.79649701},
{"learn":[0.5598347158],"iteration":212,"passed_time":19.8163066,"remaining_time":26.70084504},
{"learn":[0.5597602475],"iteration":213,"passed_time":19.91582418,"remaining_time":26.6164753},
{"learn":[0.5597093789],"iteration":214,"passed_time":20.01132243,"remaining_time":26.52663671},
{"learn":[0.5596631958],"iteration":215,"passed_time":20.10402306,"remaining_time":26.43306736},
{"learn":[0.5596044348],"iteration":216,"passed_time":20.20097035,"remaining_time":26.34504428},
{"learn":[0.559550848],"iteration":217,"passed_time":20.29848597,"remaining_time":26.25767452},
{"learn":[0.5594824921],"iteration":218,"passed_time":20.3958,"remaining_time":26.16995342},
{"learn":[0.559424668],"iteration":219,"passed_time":20.48639291,"remaining_time":26.07359098},
{"learn":[0.5593619954],"iteration":220,"passed_time":20.58182362,"remaining_time":25.98338818},
{"learn":[0.5592833057],"iteration":221,"passed_time":20.67833258,"remaining_time":25.89448855},
{"learn":[0.559207452],"iteration":222,"passed_time":20.77289249,"remaining_time":25.80309964},
{"learn":[0.5591549306],"iteration":223,"passed_time":20.86869981,"remaining_time":25.71321941},
{"learn":[0.5591050617],"iteration":224,"passed_time":20.96205586,"remaining_time":25.62029049},
{"learn":[0.5590265595],"iteration":225,"passed_time":21.05988093,"remaining_time":25.532776},
{"learn":[0.5589791519],"iteration":226,"passed_time":21.16407783,"remaining_time":25.45283369},
{"learn":[0.5589200235],"iteration":227,"passed_time":21.2831183,"remaining_time":25.39038674},
{"learn":[0.5588766835],"iteration":228,"passed_time":21.38978321,"remaining_time":25.31280022},
{"learn":[0.558841699],"iteration":229,"passed_time":21.49464316,"remaining_time":25.23284197},
{"learn":[0.5587765825],"iteration":230,"passed_time":21.59153711,"remaining_time":25.1433917},
{"learn":[0.5587150735],"iteration":231,"passed_time":21.692906,"remaining_time":25.05904658},
{"learn":[0.558680522],"iteration":232,"passed_time":21.80281999,"remaining_time":24.98434738},
{"learn":[0.5586195223],"iteration":233,"passed_time":21.90332802,"remaining_time":24.89865492},
{"learn":[0.5585854655],"iteration":234,"passed_time":22.00863447,"remaining_time":24.81824738},
{"learn":[0.5585329273],"iteration":235,"passed_time":22.09751474,"remaining_time":24.71925378},
{"learn":[0.5584795356],"iteration":236,"passed_time":22.19624373,"remaining_time":24.63127469},
{"learn":[0.5584428623],"iteration":237,"passed_time":22.29400119,"remaining_time":24.54213577},
{"learn":[0.5583785901],"iteration":238,"passed_time":22.39069853,"remaining_time":24.45176701},
{"learn":[0.55833476],"iteration":239,"passed_time":22.48823287,"remaining_time":24.36225228},
{"learn":[0.558292117],"iteration":240,"passed_time":22.58583168,"remaining_time":24.27274027},
{"learn":[0.5582230929],"iteration":241,"passed_time":22.68070909,"remaining_time":24.18026011},
{"learn":[0.5581673785],"iteration":242,"passed_time":22.7749594,"remaining_time":24.08709698},
{"learn":[0.5581122826],"iteration":243,"passed_time":22.87237521,"remaining_time":23.99724612},
{"learn":[0.5580745215],"iteration":244,"passed_time":22.96285377,"remaining_time":23.9001131},
{"learn":[0.5580437793],"iteration":245,"passed_time":23.05657998,"remaining_time":23.80638746},
{"learn":[0.5580052351],"iteration":246,"passed_time":23.15167509,"remaining_time":23.71406396},
{"learn":[0.5579472869],"iteration":247,"passed_time":23.24961029,"remaining_time":23.62460401},
{"learn":[0.557891749],"iteration":248,"passed_time":23.34761444,"remaining_time":23.53514548},
{"learn":[0.5578422004],"iteration":249,"passed_time":23.44302258,"remaining_time":23.44302258},
{"learn":[0.5577876203],"iteration":250,"passed_time":23.54078979,"remaining_time":23.35321378},
{"learn":[0.5577268504],"iteration":251,"passed_time":23.6408453,"remaining_time":23.26559379},
{"learn":[0.5576811572],"iteration":252,"passed_time":23.72803474,"remaining_time":23.16531455},
{"learn":[0.5576189856],"iteration":253,"passed_time":23.82280735,"remaining_time":23.07248271},
{"learn":[0.5575824971],"iteration":254,"passed_time":23.9143094,"remaining_time":22.97649335},
{"learn":[0.5575516211],"iteration":255,"passed_time":24.00612635,"remaining_time":22.88083918},
{"learn":[0.5575233778],"iteration":256,"passed_time":24.0953248,"remaining_time":22.78273902},
{"learn":[0.5574688167],"iteration":257,"passed_time":24.19172176,"remaining_time":22.69145994},
{"learn":[0.5574146073],"iteration":258,"passed_time":24.29427091,"remaining_time":22.60586598},
{"learn":[0.5573882829],"iteration":259,"passed_time":24.38741922,"remaining_time":22.5114639},
{"learn":[0.5573445493],"iteration":260,"passed_time":24.4834092,"remaining_time":22.41967356},
{"learn":[0.5573030191],"iteration":261,"passed_time":24.57531743,"remaining_time":22.32414332},
{"learn":[0.5572747862],"iteration":262,"passed_time":24.66993345,"remaining_time":22.23108072},
{"learn":[0.5572214164],"iteration":263,"passed_time":24.76478317,"remaining_time":22.13821526},
{"learn":[0.5571526204],"iteration":264,"passed_time":24.85882894,"remaining_time":22.04462189},
{"learn":[0.5570961709],"iteration":265,"passed_time":24.95140137,"remaining_time":21.94972902},
{"learn":[0.5570192656],"iteration":266,"passed_time":25.04725652,"remaining_time":21.85771823},
{"learn":[0.5569535914],"iteration":267,"passed_time":25.13969954,"remaining_time":21.76272498},
{"learn":[0.5568907768],"iteration":268,"passed_time":25.23747446,"remaining_time":21.67232937},
{"learn":[0.556835343],"iteration":269,"passed_time":25.33154919,"remaining_time":21.57872709},
{"learn":[0.5568312363],"iteration":270,"passed_time":25.41314747,"remaining_time":21.47457849},
{"learn":[0.55676551],"iteration":271,"passed_time":25.5094261,"remaining_time":21.38290129},
{"learn":[0.5567293281],"iteration":272,"passed_time":25.60895645,"remaining_time":21.29389419},
{"learn":[0.5566869817],"iteration":273,"passed_time":25.70719726,"remaining_time":21.20374665},
{"learn":[0.5566372947],"iteration":274,"passed_time":25.80123344,"remaining_time":21.11010009},
{"learn":[0.5565879419],"iteration":275,"passed_time":25.89458388,"remaining_time":21.01589416},
{"learn":[0.55653706],"iteration":276,"passed_time":25.99163176,"remaining_time":20.92467105},
{"learn":[0.5564823623],"iteration":277,"passed_time":26.08705749,"remaining_time":20.83211066},
{"learn":[0.5564390537],"iteration":278,"passed_time":26.18208663,"remaining_time":20.73921557},
{"learn":[0.5563794183],"iteration":279,"passed_time":26.2760496,"remaining_time":20.64546754},
{"learn":[0.5563376598],"iteration":280,"passed_time":26.37449136,"remaining_time":20.55520857},
{"learn":[0.5562834586],"iteration":281,"passed_time":26.47142431,"remaining_time":20.46372518},
{"learn":[0.5562236261],"iteration":282,"passed_time":26.5669341,"remaining_time":20.37111201},
{"learn":[0.5561680266],"iteration":283,"passed_time":26.65867245,"remaining_time":20.27561003},
{"learn":[0.556149765],"iteration":284,"passed_time":26.75637372,"remaining_time":20.18463281},
{"learn":[0.5561033101],"iteration":285,"passed_time":26.85042102,"remaining_time":20.09087447},
{"learn":[0.5560767669],"iteration":286,"passed_time":26.93987462,"remaining_time":19.99370486},
{"learn":[0.5560117291],"iteration":287,"passed_time":27.03336092,"remaining_time":19.89955734},
{"learn":[0.5559612046],"iteration":288,"passed_time":27.12227186,"remaining_time":19.80207392},
{"learn":[0.5558955951],"iteration":289,"passed_time":27.21752124,"remaining_time":19.70923952},
{"learn":[0.555837071],"iteration":290,"passed_time":27.31287078,"remaining_time":19.61646046},
{"learn":[0.5557850475],"iteration":291,"passed_time":27.40557653,"remaining_time":19.52178054},
{"learn":[0.555742621],"iteration":292,"passed_time":27.50216322,"remaining_time":19.42985593},
{"learn":[0.5556589614],"iteration":293,"passed_time":27.5945998,"remaining_time":19.3349917},
{"learn":[0.5556067384],"iteration":294,"passed_time":27.6896807,"remaining_time":19.2419815},
{"learn":[0.5555621654],"iteration":295,"passed_time":27.78534626,"remaining_time":19.14936026},
{"learn":[0.5555136359],"iteration":296,"passed_time":27.88310355,"remaining_time":19.05814822},
{"learn":[0.5554438783],"iteration":297,"passed_time":27.98420101,"remaining_time":18.96915639},
{"learn":[0.555394365],"iteration":298,"passed_time":28.08138334,"remaining_time":18.87745168},
{"learn":[0.5553405781],"iteration":299,"passed_time":28.17703169,"remaining_time":18.7846878},
{"learn":[0.55527868],"iteration":300,"passed_time":28.27462521,"remaining_time":18.69319076},
{"learn":[0.5552278988],"iteration":301,"passed_time":28.37049562,"remaining_time":18.60052362},
{"learn":[0.5551744211],"iteration":302,"passed_time":28.460923,"remaining_time":18.50429647},
{"learn":[0.5551237846],"iteration":303,"passed_time":28.55426681,"remaining_time":18.40998781},
{"learn":[0.5550621732],"iteration":304,"passed_time":28.64986335,"remaining_time":18.31712575},
{"learn":[0.5550119152],"iteration":305,"passed_time":28.7459807,"remaining_time":18.224576},
{"learn":[0.55495392],"iteration":306,"passed_time":28.83954373,"remaining_time":18.1303972},
{"learn":[0.5549293542],"iteration":307,"passed_time":28.93519166,"remaining_time":18.03752207},
{"learn":[0.554883486],"iteration":308,"passed_time":29.03020254,"remaining_time":17.94423523},
{"learn":[0.5548668491],"iteration":309,"passed_time":29.13198508,"remaining_time":17.85508763},
{"learn":[0.5548116717],"iteration":310,"passed_time":29.22794347,"remaining_time":17.76231934},
{"learn":[0.5547704382],"iteration":311,"passed_time":29.32282637,"remaining_time":17.66888256},
{"learn":[0.5547043595],"iteration":312,"passed_time":29.41402435,"remaining_time":17.57323499},
{"learn":[0.55464204],"iteration":313,"passed_time":29.50223084,"remaining_time":17.47584374},
{"learn":[0.5545675862],"iteration":314,"passed_time":29.59935441,"remaining_time":17.38374783},
{"learn":[0.5545326145],"iteration":315,"passed_time":29.69212481,"remaining_time":17.28908533},
{"learn":[0.554492149],"iteration":316,"passed_time":29.78299394,"remaining_time":17.19333719},
{"learn":[0.5544216602],"iteration":317,"passed_time":29.88004183,"remaining_time":17.10115602},
{"learn":[0.5543687212],"iteration":318,"passed_time":29.97925854,"remaining_time":17.01017491},
{"learn":[0.5543277633],"iteration":319,"passed_time":30.07348357,"remaining_time":16.91633451},
{"learn":[0.5542916521],"iteration":320,"passed_time":30.16892426,"remaining_time":16.8231696},
{"learn":[0.5542471592],"iteration":321,"passed_time":30.26733207,"remaining_time":16.73163077},
{"learn":[0.5542003355],"iteration":322,"passed_time":30.36153794,"remaining_time":16.6377468},
{"learn":[0.554152875],"iteration":323,"passed_time":30.45687946,"remaining_time":16.54447773},
{"learn":[0.5541009749],"iteration":324,"passed_time":30.55158133,"remaining_time":16.45085148},
{"learn":[0.5540680385],"iteration":325,"passed_time":30.64490626,"remaining_time":16.35648371},
{"learn":[0.5540267144],"iteration":326,"passed_time":30.74040179,"remaining_time":16.26327067},
{"learn":[0.5539834693],"iteration":327,"passed_time":30.83491657,"remaining_time":16.16952942},
{"learn":[0.5539397253],"iteration":328,"passed_time":30.92456955,"remaining_time":16.07325651},
{"learn":[0.5538784933],"iteration":329,"passed_time":31.02218212,"remaining_time":15.98112412},
{"learn":[0.5538338173],"iteration":330,"passed_time":31.11714664,"remaining_time":15.88760659},
{"learn":[0.5537905029],"iteration":331,"passed_time":31.21383289,"remaining_time":15.79495158},
{"learn":[0.5537403972],"iteration":332,"passed_time":31.31108605,"remaining_time":15.70255667},
{"learn":[0.5536884862],"iteration":333,"passed_time":31.40196134,"remaining_time":15.60696282},
{"learn":[0.5536387464],"iteration":334,"passed_time":31.49729161,"remaining_time":15.51359139},
{"learn":[0.5535790839],"iteration":335,"passed_time":31.59594852,"remaining_time":15.42183202},
{"learn":[0.5535267204],"iteration":336,"passed_time":31.68980782,"remaining_time":15.3277112},
{"learn":[0.5534650873],"iteration":337,"passed_time":31.78107763,"remaining_time":15.23235082},
{"learn":[0.5534393123],"iteration":338,"passed_time":31.87203149,"remaining_time":15.13686451},
{"learn":[0.5533869874],"iteration":339,"passed_time":31.96864341,"remaining_time":15.04406749},
{"learn":[0.5533317606],"iteration":340,"passed_time":32.06665117,"remaining_time":14.95189893},
{"learn":[0.5532764151],"iteration":341,"passed_time":32.16251468,"remaining_time":14.85870561},
{"learn":[0.5532280116],"iteration":342,"passed_time":32.25967772,"remaining_time":14.76609155},
{"learn":[0.5531610948],"iteration":343,"passed_time":32.36080605,"remaining_time":14.67524926},
{"learn":[0.5530937374],"iteration":344,"passed_time":32.45762027,"remaining_time":14.58240911},
{"learn":[0.5530414055],"iteration":345,"passed_time":32.55590272,"remaining_time":14.49019947},
{"learn":[0.5529676297],"iteration":346,"passed_time":32.65281123,"remaining_time":14.39734905},
{"learn":[0.552911688],"iteration":347,"passed_time":32.74891996,"remaining_time":14.30412596},
{"learn":[0.552862723],"iteration":348,"passed_time":32.84175026,"remaining_time":14.20946788},
{"learn":[0.5528324045],"iteration":349,"passed_time":32.93524747,"remaining_time":14.11510606},
{"learn":[0.5528077244],"iteration":350,"passed_time":33.02824118,"remaining_time":14.02053543},
{"learn":[0.5527402096],"iteration":351,"passed_time":33.12701378,"remaining_time":13.92840352},
{"learn":[0.5526968887],"iteration":352,"passed_time":33.22563034,"remaining_time":13.83616901},
{"learn":[0.5526603579],"iteration":353,"passed_time":33.32197843,"remaining_time":13.74296285},
{"learn":[0.5526396448],"iteration":354,"passed_time":33.41888795,"remaining_time":13.64996832},
{"learn":[0.5526006006],"iteration":355,"passed_time":33.51506782,"remaining_time":13.55665665},
{"learn":[0.5525612518],"iteration":356,"passed_time":33.60934937,"remaining_time":13.46256851},
{"learn":[0.5525125005],"iteration":357,"passed_time":33.70656081,"remaining_time":13.36964144},
{"learn":[0.5524649754],"iteration":358,"passed_time":33.80500875,"remaining_time":13.27717614},
{"learn":[0.5524378371],"iteration":359,"passed_time":33.90585217,"remaining_time":13.18560918},
{"learn":[0.5524101688],"iteration":360,"passed_time":33.99917973,"remaining_time":13.0910969},
{"learn":[0.5523582466],"iteration":361,"passed_time":34.09560125,"remaining_time":12.99777064},
{"learn":[0.552309696],"iteration":362,"passed_time":34.18972531,"remaining_time":12.90356024},
{"learn":[0.5522512446],"iteration":363,"passed_time":34.28592602,"remaining_time":12.8101262},
{"learn":[0.552210865],"iteration":364,"passed_time":34.3739371,"remaining_time":12.71364797},
{"learn":[0.5521918465],"iteration":365,"passed_time":34.47391895,"remaining_time":12.62159874},
{"learn":[0.5521213986],"iteration":366,"passed_time":34.56953406,"remaining_time":12.52792379},
{"learn":[0.5520774174],"iteration":367,"passed_time":34.66392429,"remaining_time":12.43379893},
{"learn":[0.5520360353],"iteration":368,"passed_time":34.75769502,"remaining_time":12.3394527},
{"learn":[0.5519924447],"iteration":369,"passed_time":34.85104702,"remaining_time":12.24496247},
{"learn":[0.551948284],"iteration":370,"passed_time":34.94747003,"remaining_time":12.15154618},
{"learn":[0.5518989065],"iteration":371,"passed_time":35.03670821,"remaining_time":12.05564154},
{"learn":[0.551858074],"iteration":372,"passed_time":35.13521367,"remaining_time":11.96292798},
{"learn":[0.5518287852],"iteration":373,"passed_time":35.22725395,"remaining_time":11.86800534},
{"learn":[0.5518005931],"iteration":374,"passed_time":35.31998588,"remaining_time":11.77332863},
{"learn":[0.5517584402],"iteration":375,"passed_time":35.41336071,"remaining_time":11.67887428},
{"learn":[0.5517182433],"iteration":376,"passed_time":35.50817664,"remaining_time":11.58489583},
{"learn":[0.5516543632],"iteration":377,"passed_time":35.60592036,"remaining_time":11.49185789},
{"learn":[0.5516269108],"iteration":378,"passed_time":35.70188114,"remaining_time":11.3982259},
{"learn":[0.551590536],"iteration":379,"passed_time":35.79804013,"remaining_time":11.30464425},
{"learn":[0.551529657],"iteration":380,"passed_time":35.89530279,"remaining_time":11.21139378},
{"learn":[0.5514737302],"iteration":381,"passed_time":35.99269949,"remaining_time":11.11816372},
{"learn":[0.551421693],"iteration":382,"passed_time":36.08794004,"remaining_time":11.02425322},
{"learn":[0.5513613275],"iteration":383,"passed_time":36.18536414,"remaining_time":10.93099542},
{"learn":[0.5513198029],"iteration":384,"passed_time":36.27932187,"remaining_time":10.83668056},
{"learn":[0.551293448],"iteration":385,"passed_time":36.37369595,"remaining_time":10.74249051},
{"learn":[0.5512356115],"iteration":386,"passed_time":36.46734936,"remaining_time":10.64808909},
{"learn":[0.5511799652],"iteration":387,"passed_time":36.56187537,"remaining_time":10.55394341},
{"learn":[0.5511491519],"iteration":388,"passed_time":36.65644457,"remaining_time":10.45980809},
{"learn":[0.5511197213],"iteration":389,"passed_time":36.74956606,"remaining_time":10.36526222},
{"learn":[0.5510745823],"iteration":390,"passed_time":36.84326325,"remaining_time":10.27088413},
{"learn":[0.5510041258],"iteration":391,"passed_time":36.93340728,"remaining_time":10.17553058},
{"learn":[0.5509799695],"iteration":392,"passed_time":37.03058159,"remaining_time":10.08211763},
{"learn":[0.5509193545],"iteration":393,"passed_time":37.12828687,"remaining_time":9.988828447},
{"learn":[0.5508726318],"iteration":394,"passed_time":37.2243886,"remaining_time":9.895090641},
{"learn":[0.550830528],"iteration":395,"passed_time":37.32243933,"remaining_time":9.801852755},
{"learn":[0.5507790907],"iteration":396,"passed_time":37.42295223,"remaining_time":9.709229419},
{"learn":[0.5507347545],"iteration":397,"passed_time":37.51392328,"remaining_time":9.614121041},
{"learn":[0.550693741],"iteration":398,"passed_time":37.61154598,"remaining_time":9.520717152},
{"learn":[0.5506269584],"iteration":399,"passed_time":37.70571318,"remaining_time":9.426428295},
{"learn":[0.5505869081],"iteration":400,"passed_time":37.80163978,"remaining_time":9.332574409},
{"learn":[0.5505559467],"iteration":401,"passed_time":37.89573545,"remaining_time":9.238263867},
{"learn":[0.550484649],"iteration":402,"passed_time":37.99705596,"remaining_time":9.145693369},
{"learn":[0.5504111507],"iteration":403,"passed_time":38.09670652,"remaining_time":9.052682738},
{"learn":[0.5503633388],"iteration":404,"passed_time":38.19274015,"remaining_time":8.9587909},
{"learn":[0.5503113087],"iteration":405,"passed_time":38.29395386,"remaining_time":8.86608784},
{"learn":[0.5502640782],"iteration":406,"passed_time":38.38755745,"remaining_time":8.771604037},
{"learn":[0.5502275829],"iteration":407,"passed_time":38.48830925,"remaining_time":8.678736401},
{"learn":[0.5502047317],"iteration":408,"passed_time":38.58597407,"remaining_time":8.585143375},
{"learn":[0.5501409505],"iteration":409,"passed_time":38.68280522,"remaining_time":8.491347488},
{"learn":[0.5501041465],"iteration":410,"passed_time":38.77789315,"remaining_time":8.397159343},
{"learn":[0.5500544349],"iteration":411,"passed_time":38.86602255,"remaining_time":8.301480544},
{"learn":[0.5500279958],"iteration":412,"passed_time":38.95767711,"remaining_time":8.206580893},
{"learn":[0.5499705352],"iteration":413,"passed_time":39.05897843,"remaining_time":8.113700834},
{"learn":[0.5499131179],"iteration":414,"passed_time":39.15615109,"remaining_time":8.01993456},
{"learn":[0.5498887923],"iteration":415,"passed_time":39.24808265,"remaining_time":7.925093612},
{"learn":[0.549822517],"iteration":416,"passed_time":39.33956123,"remaining_time":7.830176457},
{"learn":[0.5497970856],"iteration":417,"passed_time":39.43610617,"remaining_time":7.736269631},
{"learn":[0.5497276025],"iteration":418,"passed_time":39.52923844,"remaining_time":7.641690486},
{"learn":[0.5496767628],"iteration":419,"passed_time":39.64218377,"remaining_time":7.550892147},
{"learn":[0.5496338627],"iteration":420,"passed_time":39.73618238,"remaining_time":7.456433274},
{"learn":[0.5495893393],"iteration":421,"passed_time":39.82994431,"remaining_time":7.361932834},
{"learn":[0.5495291078],"iteration":422,"passed_time":39.92559441,"remaining_time":7.267779597},
{"learn":[0.5494703608],"iteration":423,"passed_time":40.02364658,"remaining_time":7.174049859},
{"learn":[0.5494214773],"iteration":424,"passed_time":40.11945788,"remaining_time":7.079904332},
{"learn":[0.5493791275],"iteration":425,"passed_time":40.21627876,"remaining_time":6.985926358},
{"learn":[0.5493317498],"iteration":426,"passed_time":40.31078625,"remaining_time":6.89153957},
{"learn":[0.5493058835],"iteration":427,"passed_time":40.40507516,"remaining_time":6.797115448},
{"learn":[0.5492511775],"iteration":428,"passed_time":40.49522212,"remaining_time":6.702006458},
{"learn":[0.5491875348],"iteration":429,"passed_time":40.59051344,"remaining_time":6.607758003},
{"learn":[0.5491534116],"iteration":430,"passed_time":40.68696814,"remaining_time":6.513690955},
{"learn":[0.5490914308],"iteration":431,"passed_time":40.78029107,"remaining_time":6.41911989},
{"learn":[0.5490431752],"iteration":432,"passed_time":40.87353013,"remaining_time":6.324541613},
{"learn":[0.5489976473],"iteration":433,"passed_time":40.97087199,"remaining_time":6.230593437},
{"learn":[0.5489245248],"iteration":434,"passed_time":41.06603042,"remaining_time":6.136303396},
{"learn":[0.5488986733],"iteration":435,"passed_time":41.16546218,"remaining_time":6.042636651},
{"learn":[0.5488498937],"iteration":436,"passed_time":41.255823,"remaining_time":5.947635811},
{"learn":[0.5488279232],"iteration":437,"passed_time":41.35323427,"remaining_time":5.853654166},
{"learn":[0.5487516729],"iteration":438,"passed_time":41.44309232,"remaining_time":5.758607362},
{"learn":[0.5487189677],"iteration":439,"passed_time":41.53816695,"remaining_time":5.664295493},
{"learn":[0.5486597732],"iteration":440,"passed_time":41.63015266,"remaining_time":5.569566909},
{"learn":[0.5486180289],"iteration":441,"passed_time":41.72857745,"remaining_time":5.475695684},
{"learn":[0.5486150772],"iteration":442,"passed_time":41.8221492,"remaining_time":5.381179468},
{"learn":[0.5485805475],"iteration":443,"passed_time":41.9220833,"remaining_time":5.287469966},
{"learn":[0.5485060274],"iteration":444,"passed_time":42.02043398,"remaining_time":5.193536785},
{"learn":[0.5484387966],"iteration":445,"passed_time":42.11577985,"remaining_time":5.099219982},
{"learn":[0.5484005021],"iteration":446,"passed_time":42.21339644,"remaining_time":5.00516781},
{"learn":[0.548363653],"iteration":447,"passed_time":42.31394109,"remaining_time":4.91143959},
{"learn":[0.5483234135],"iteration":448,"passed_time":42.41439798,"remaining_time":4.81767104},
{"learn":[0.5482789813],"iteration":449,"passed_time":42.51157203,"remaining_time":4.723508004},
{"learn":[0.5482432286],"iteration":450,"passed_time":42.60584373,"remaining_time":4.629016281},
{"learn":[0.5481867851],"iteration":451,"passed_time":42.70193243,"remaining_time":4.534718488},
{"learn":[0.5481373271],"iteration":452,"passed_time":42.7976425,"remaining_time":4.440373504},
{"learn":[0.5481025281],"iteration":453,"passed_time":42.89165931,"remaining_time":4.345850944},
{"learn":[0.5480690729],"iteration":454,"passed_time":42.98888952,"remaining_time":4.251648415},
{"learn":[0.5480282681],"iteration":455,"passed_time":43.08324769,"remaining_time":4.157155479},
{"learn":[0.5479695649],"iteration":456,"passed_time":43.17730004,"remaining_time":4.062634358},
{"learn":[0.5479269279],"iteration":457,"passed_time":43.2680401,"remaining_time":3.967811538},
{"learn":[0.5478696377],"iteration":458,"passed_time":43.3620312,"remaining_time":3.873296905},
{"learn":[0.5478250068],"iteration":459,"passed_time":43.45714954,"remaining_time":3.778882569},
{"learn":[0.5477898668],"iteration":460,"passed_time":43.55953625,"remaining_time":3.685080073},
{"learn":[0.5477423263],"iteration":461,"passed_time":43.65559177,"remaining_time":3.590719669},
{"learn":[0.5476741768],"iteration":462,"passed_time":43.74986152,"remaining_time":3.496209236},
{"learn":[0.5476463948],"iteration":463,"passed_time":43.84671176,"remaining_time":3.40190005},
{"learn":[0.54761553],"iteration":464,"passed_time":43.94543022,"remaining_time":3.307720554},
{"learn":[0.5475770893],"iteration":465,"passed_time":44.04666196,"remaining_time":3.21370495},
{"learn":[0.5475318934],"iteration":466,"passed_time":44.14177993,"remaining_time":3.119226419},
{"learn":[0.547477127],"iteration":467,"passed_time":44.23878183,"remaining_time":3.024873971},
{"learn":[0.5474344405],"iteration":468,"passed_time":44.33468286,"remaining_time":2.93043746},
{"learn":[0.547395253],"iteration":469,"passed_time":44.42427671,"remaining_time":2.83559213},
{"learn":[0.5473467824],"iteration":470,"passed_time":44.52199468,"remaining_time":2.741269312},
{"learn":[0.5473154512],"iteration":471,"passed_time":44.62259009,"remaining_time":2.647102802},
{"learn":[0.5472687452],"iteration":472,"passed_time":44.71710496,"remaining_time":2.552562017},
{"learn":[0.5472189682],"iteration":473,"passed_time":44.81277397,"remaining_time":2.458084648},
{"learn":[0.5472026228],"iteration":474,"passed_time":44.906832,"remaining_time":2.363517474},
{"learn":[0.5471683965],"iteration":475,"passed_time":45.00191361,"remaining_time":2.269004048},
{"learn":[0.5471210193],"iteration":476,"passed_time":45.09602665,"remaining_time":2.174441537},
{"learn":[0.5470788529],"iteration":477,"passed_time":45.19284501,"remaining_time":2.080005419},
{"learn":[0.5470485584],"iteration":478,"passed_time":45.28200245,"remaining_time":1.985223489},
{"learn":[0.5470066971],"iteration":479,"passed_time":45.38039781,"remaining_time":1.890849909},
{"learn":[0.546968193],"iteration":480,"passed_time":45.47514756,"remaining_time":1.7963156},
{"learn":[0.5469130821],"iteration":481,"passed_time":45.57346417,"remaining_time":1.7019136},
{"learn":[0.5468795216],"iteration":482,"passed_time":45.67239905,"remaining_time":1.607517151},
{"learn":[0.546843116],"iteration":483,"passed_time":45.76555861,"remaining_time":1.512911028},
{"learn":[0.54679646],"iteration":484,"passed_time":45.85555245,"remaining_time":1.418212962},
{"learn":[0.5467590202],"iteration":485,"passed_time":45.95635384,"remaining_time":1.323845584},
{"learn":[0.5467401176],"iteration":486,"passed_time":46.0492588,"remaining_time":1.229240995},
{"learn":[0.5467055419],"iteration":487,"passed_time":46.14412697,"remaining_time":1.134691647},
{"learn":[0.5466717222],"iteration":488,"passed_time":46.24123114,"remaining_time":1.040191294},
{"learn":[0.5466516869],"iteration":489,"passed_time":46.33756594,"remaining_time":0.945664611},
{"learn":[0.5466058626],"iteration":490,"passed_time":46.43264233,"remaining_time":0.851107497},
{"learn":[0.5465610798],"iteration":491,"passed_time":46.52810131,"remaining_time":0.7565544928},
{"learn":[0.5465106842],"iteration":492,"passed_time":46.6230033,"remaining_time":0.6619899049},
{"learn":[0.5464846418],"iteration":493,"passed_time":46.72318243,"remaining_time":0.5674880456},
{"learn":[0.5464379103],"iteration":494,"passed_time":46.81678899,"remaining_time":0.4728968585},
{"learn":[0.5463905],"iteration":495,"passed_time":46.90845813,"remaining_time":0.3782940172},
{"learn":[0.5463484814],"iteration":496,"passed_time":47.00726896,"remaining_time":0.2837460903},
{"learn":[0.5463009828],"iteration":497,"passed_time":47.09735366,"remaining_time":0.1891459987},
{"learn":[0.5462730881],"iteration":498,"passed_time":47.19257735,"remaining_time":0.0945743033},
{"learn":[0.546245074],"iteration":499,"passed_time":47.28645237,"remaining_time":0}
]}